xinference_client/__init__.py
xinference_client/_compat.py
xinference_client/_version.py
xinference_client/fields.py
xinference_client/types.py
xinference_client/client/__init__.py
xinference_client/client/common.py
xinference_client/client/restful/__init__.py
xinference_client/client/restful/async_restful_client.py
xinference_client/client/restful/restful_client.py
xinference_client-2.0.0.dist-info/licenses/LICENSE
xinference_client-2.0.0.dist-info/METADATA
xinference_client-2.0.0.dist-info/WHEEL
xinference_client-2.0.0.dist-info/top_level.txt
xinference_client-2.0.0.dist-info/RECORD
